subjective_logic/__init__.py
subjective_logic/__main__.py
subjective_logic/binomial_opinion.py
subjective_logic-1.0.2.dist-info/licenses/LICENSE
subjective_logic-1.0.2.dist-info/METADATA
subjective_logic-1.0.2.dist-info/WHEEL
subjective_logic-1.0.2.dist-info/top_level.txt
subjective_logic-1.0.2.dist-info/RECORD
