Metadata-Version: 2.4
Name: subjective_logic
Version: 1.0.2
Summary: A Python implementation of subjective logic.
Author-email: Waleed Khan <waleedqk@gmail.com>
Maintainer-email: Waleed Khan <waleedqk@gmail.com>
License: MIT License
Project-URL: Homepage, https://github.com/waleedqk/subjective-logic
Project-URL: Documentation, https://github.com/waleedqk/subjective-logic/blob/main/README.md
Project-URL: Repository, https://github.com/waleedqk/subjective-logic
Project-URL: Issues, https://github.com/waleedqk/subjective-logic/issues
Project-URL: Changelog, https://github.com/waleedqk/subjective-logic/CHANGELOG.md
Keywords: subjective logic,opinion,python
Classifier: Programming Language :: Python :: 3
Classifier: License :: OSI Approved :: MIT License
Classifier: Operating System :: OS Independent
Requires-Python: >=3.10
License-File: LICENSE
Requires-Dist: numpy>=1.24.0
Provides-Extra: dev
Requires-Dist: tox; extra == "dev"
Requires-Dist: black; extra == "dev"
Provides-Extra: doc
Requires-Dist: sphinx; extra == "doc"
Requires-Dist: sphinx-rtd-theme; extra == "doc"
Provides-Extra: test
Requires-Dist: pytest>=6.0; extra == "test"
Requires-Dist: pytest-cov; extra == "test"
Dynamic: license-file
